phic-2.1.3.dist-info/licenses/LICENSE
src/__init__.py
src/phic2.py
phic-2.1.3.dist-info/METADATA
phic-2.1.3.dist-info/WHEEL
phic-2.1.3.dist-info/entry_points.txt
phic-2.1.3.dist-info/top_level.txt
phic-2.1.3.dist-info/RECORD
