Metadata-Version: 2.4
Name: phic
Version: 2.1.3
Summary: Polymer dynamics simulation from Hi-C data
Home-page: https://github.com/soyashinkai/PHi-C2
Author: Soya SHINKAI and Soya HAGIWARA
Author-email: soya.shinkai@riken.jp
License: GPL-3.0
Keywords: biophysics,bioinformatics,genomics,Hi-C,polymer modeling,polymer dynamics,rheology
Classifier: Programming Language :: Python :: 3
Classifier: License :: OSI Approved :: GNU General Public License v3 (GPLv3)
Classifier: Operating System :: OS Independent
License-File: LICENSE
Requires-Dist: numpy
Requires-Dist: matplotlib
Requires-Dist: scipy
Requires-Dist: click
Requires-Dist: pandas
Requires-Dist: hic-straw
Requires-Dist: cooler
Requires-Dist: h5py
Dynamic: author
Dynamic: author-email
Dynamic: classifier
Dynamic: description
Dynamic: description-content-type
Dynamic: home-page
Dynamic: keywords
Dynamic: license
Dynamic: license-file
Dynamic: requires-dist
Dynamic: summary
